{
 "actions": [],
 "creation": "2026-02-27 00:00:00.000000",
 "doctype": "DocType",
 "editable_grid": 1,
 "engine": "InnoDB",
 "field_order": [
  "document_type",
  "document_number",
  "first_name",
  "last_name",
  "license_number",
  "raw"
 ],
 "fields": [
  {
   "fieldname": "document_type",
   "fieldtype": "Select",
   "in_list_view": 1,
   "label": "Document Type",
    "options": "1\n4\n7"
  },
  {
   "fieldname": "document_number",
   "fieldtype": "Data",
   "in_list_view": 1,
    "label": "Document Number"
  },
  {
   "fieldname": "first_name",
   "fieldtype": "Data",
   "in_list_view": 1,
    "label": "First Name"
  },
  {
   "fieldname": "last_name",
   "fieldtype": "Data",
   "in_list_view": 1,
    "label": "Last Name"
  },
  {
   "fieldname": "license_number",
   "fieldtype": "Data",
   "in_list_view": 1,
    "label": "License Number"
  },
  {
   "fieldname": "raw",
   "fieldtype": "JSON",
   "label": "Raw"
  }
 ],
 "grid_page_length": 50,
 "index_web_pages_for_search": 1,
 "istable": 1,
 "links": [],
 "modified": "2026-02-27 00:00:00.000000",
 "modified_by": "Administrator",
 "module": "Nubefact",
 "name": "Nubefact Delivery Note Secondary Driver",
 "owner": "Administrator",
 "permissions": [],
 "row_format": "Dynamic",
 "rows_threshold_for_grid_search": 20,
 "sort_field": "modified",
 "sort_order": "DESC",
 "states": []
}
